lsegkd/__init__.py
lsegkd/cli.py
lsegkd/api/__init__.py
lsegkd/api/utils.py
lsegkd/api/auth/__init__.py
lsegkd/api/auth/credentials.py
lsegkd/api/services/__init__.py
lsegkd/api/services/base/__init__.py
lsegkd/api/services/base/client.py
lsegkd/api/services/base/method.py
lsegkd/api/services/street_events/__init__.py
lsegkd/api/services/street_events/client.py
lsegkd/api/services/street_events/methods/__init__.py
lsegkd/api/services/street_events/methods/_get_document_result.py
lsegkd/api/services/street_events/methods/_get_event_headlines.py
lsegkd/api/services/token_management/__init__.py
lsegkd/api/services/token_management/client.py
lsegkd/api/services/token_management/methods/__init__.py
lsegkd/api/services/token_management/methods/_create_service_token.py
lsegkd/xml/__init__.py
lsegkd/xml/transcript.py
lsegkd-0.1.0.dist-info/METADATA
lsegkd-0.1.0.dist-info/WHEEL
lsegkd-0.1.0.dist-info/entry_points.txt
lsegkd-0.1.0.dist-info/licenses/LICENSE
lsegkd-0.1.0.dist-info/RECORD
