Metadata-Version: 2.4
Name: lsegkd
Version: 0.1.0
Summary: A Python library for retrieving financial data using the LSEG Knowledge Direct API
Project-URL: Homepage, https://github.com/yurukatsu/lseg-knowledge-direct
Project-URL: Repository, https://github.com/yurukatsu/lseg-knowledge-direct
Project-URL: Issues, https://github.com/yurukatsu/lseg-knowledge-direct/issues
Author-email: Your Name <your.email@example.com>
License-Expression: MIT
License-File: LICENSE
Keywords: api,data,finance,lseg
Classifier: Development Status :: 3 - Alpha
Classifier: Intended Audience :: Developers
Classifier: License :: OSI Approved :: MIT License
Classifier: Programming Language :: Python :: 3
Classifier: Programming Language :: Python :: 3.12
Classifier: Topic :: Office/Business :: Financial
Classifier: Topic :: Software Development :: Libraries :: Python Modules
Requires-Python: >=3.12
Requires-Dist: click>=8.3.1
Requires-Dist: httpx>=0.28.1
Requires-Dist: loguru>=0.7.3
Requires-Dist: pydantic>=2.12.5
Requires-Dist: python-dotenv>=1.2.1
Requires-Dist: requests>=2.32.5
